django_cookie_control/__init__.py
django_cookie_control/admin.py
django_cookie_control/apps.py
django_cookie_control/cache.py
django_cookie_control/models.py
django_cookie_control/receivers.py
django_cookie_control/settings.py
django_cookie_control/migrations/0001_initial.py
django_cookie_control/migrations/0002_add_default_cookies.py
django_cookie_control/migrations/0003_auto_20190606_1254.py
django_cookie_control/migrations/0004_auto_20190819_1656.py
django_cookie_control/migrations/0005_auto_20200131_1645.py
django_cookie_control/migrations/0006_auto_20200422_1250.py
django_cookie_control/migrations/0007_auto_20200820_1650.py
django_cookie_control/migrations/0008_auto_20200820_1651.py
django_cookie_control/migrations/0009_auto_20200821_1118.py
django_cookie_control/migrations/0010_cookiecontrol_is_enabled.py
django_cookie_control/migrations/0011_auto_20200904_1119.py
django_cookie_control/migrations/0012_auto_20220514_1707.py
django_cookie_control/migrations/0013_auto_20220514_1847.py
django_cookie_control/migrations/0014_auto_20230313_1435.py
django_cookie_control/migrations/__init__.py
django_cookie_control/static/django_cookie_control/js/cookie-enable-disable.js
django_cookie_control/static/django_cookie_control/js/cookie-enable-disable.min.js
django_cookie_control/templates/django_cookie_control/cookie-control.html
django_cookie_control/templatetags/__init__.py
django_cookie_control/templatetags/cookie_control.py
django_cookie_control-9.6.1.dist-info/LICENSE
django_cookie_control-9.6.1.dist-info/METADATA
django_cookie_control-9.6.1.dist-info/WHEEL
django_cookie_control-9.6.1.dist-info/top_level.txt
django_cookie_control-9.6.1.dist-info/RECORD
