Metadata-Version: 2.1
Name: django-cookie-control
Version: 9.6.1
Summary: Django plugin to add and configure the Cookie Control by Civic UK
Home-page: https://github.com/mcldev/django-cookie-control
Author: Civic UK, Michael Carder Ltd
Author-email: codetoolbox@michaelcarder.co.uk
License: MIT License
Classifier: Environment :: Web Environment
Classifier: Intended Audience :: Developers
Classifier: License :: OSI Approved :: MIT License
Classifier: Operating System :: OS Independent
Classifier: Framework :: Django
Classifier: Framework :: Django :: 2.2
Classifier: Framework :: Django :: 3.2
Classifier: Programming Language :: Python
Classifier: Programming Language :: Python :: 3.6
Classifier: Programming Language :: Python :: 3.7
Classifier: Programming Language :: Python :: 3.8
Classifier: Programming Language :: Python :: 3.9
Classifier: Topic :: Internet :: WWW/HTTP
Classifier: Topic :: Internet :: WWW/HTTP :: Dynamic Content
License-File: LICENSE
Requires-Dist: django (>=2.2)
Requires-Dist: django-parler
Requires-Dist: django-filer
Requires-Dist: django-countries
Requires-Dist: django-colorfield
